cobra_ssg/__init__.py
cobra_ssg/cli.py
cobra_ssg/cobra_ssg.py
cobra_ssg/cobra_utils.py
cobra_ssg-0.1.3.dist-info/LICENSE
cobra_ssg-0.1.3.dist-info/METADATA
cobra_ssg-0.1.3.dist-info/WHEEL
cobra_ssg-0.1.3.dist-info/entry_points.txt
cobra_ssg-0.1.3.dist-info/RECORD
