Metadata-Version: 2.1
Name: cobra-ssg
Version: 0.1.3
Summary: Simple static site generator developed using TDD
Author: Juan Lucha
Author-email: juanlucha@gmail.com
Requires-Python: >=3.12,<4.0
Classifier: Programming Language :: Python :: 3
Classifier: Programming Language :: Python :: 3.12
Requires-Dist: Markdown (>=3.7,<4.0)
Requires-Dist: python-frontmatter (>=1.1.0,<2.0.0)
